actionkit/__init__.py
actionkit/context_processors.py
actionkit/models.py
actionkit/rest.py
actionkit/urls.py
actionkit/utils.py
actionkit/views.py
django_actionkit_client-0.19.1.dist-info/LICENSE.txt
django_actionkit_client-0.19.1.dist-info/LICENSE.txt~
django_actionkit_client-0.19.1.dist-info/METADATA
django_actionkit_client-0.19.1.dist-info/WHEEL
django_actionkit_client-0.19.1.dist-info/entry_points.txt
django_actionkit_client-0.19.1.dist-info/top_level.txt
django_actionkit_client-0.19.1.dist-info/RECORD
