Metadata-Version: 2.1
Name: django-actionkit-client
Version: 0.19.1
Summary: A Django wrapper around Actionkit's MySQL client-db, REST API and XML-RPC API
Home-page: UNKNOWN
Author: Ethan Jucovy
Author-email: UNKNOWN
License: BSD
Platform: UNKNOWN
Requires-Dist: requests
